{
    "timestamp": "2025-07-01 09:14:45",
    "cum_gam": 7362.548262548263,
    "cum_vec": 7362.548262548263,
    "DEX_Call": 78.126,
    "DEX_Put": -85.64,
    "DEX_Total": -7.514,
    "DEX_Ratio": 0.912261,
    "GEX_Call": 2208568.068,
    "GEX_Put": -2876878.828,
    "GEX_Total": -668310.76,
    "GEX_Ratio": 0.767696,
    "VEX_Call": -456433.62,
    "VEX_Put": 810822.657,
    "VEX_Total": 354389.037,
    "VEX_Ratio": -0.562927,
    "CEX_Call": -16529441.259,
    "CEX_Put": 28301070.599,
    "CEX_Total": 11771629.34,
    "CEX_Ratio": -0.584057
}