{
    "timestamp": "2025-10-01 12:30:37",
    "cum_gam": null,
    "cum_vec": 8600.0,
    "DEX_Call": 331.071,
    "DEX_Put": -5.08,
    "DEX_Total": 325.991,
    "DEX_Ratio": 65.171457,
    "GEX_Call": 4060332.813,
    "GEX_Put": -465240.682,
    "GEX_Total": 3595092.131,
    "GEX_Ratio": 8.727381,
    "VEX_Call": 171714.332,
    "VEX_Put": 190688.308,
    "VEX_Total": 362402.64,
    "VEX_Ratio": 0.900497,
    "CEX_Call": 15475428.705,
    "CEX_Put": 17817135.875,
    "CEX_Total": 33292564.58,
    "CEX_Ratio": 0.86857
}