{
    "timestamp": "2025-10-16 11:49:19",
    "cum_gam": 6651.539628246421,
    "cum_vec": 6651.539628246421,
    "DEX_Call": 34.749,
    "DEX_Put": -192.202,
    "DEX_Total": -157.453,
    "DEX_Ratio": 0.180794,
    "GEX_Call": 576626.942,
    "GEX_Put": -1813622.241,
    "GEX_Total": -1236995.299,
    "GEX_Ratio": 0.317942,
    "VEX_Call": -189043.499,
    "VEX_Put": 204747.205,
    "VEX_Total": 15703.706,
    "VEX_Ratio": -0.923302,
    "CEX_Call": -12987597.831,
    "CEX_Put": 13685581.078,
    "CEX_Total": 697983.247,
    "CEX_Ratio": -0.948999
}