{
    "timestamp": "2025-09-11 10:24:35",
    "cum_gam": null,
    "cum_vec": 7381.684981684982,
    "DEX_Call": 269.159,
    "DEX_Put": -9.403,
    "DEX_Total": 259.756,
    "DEX_Ratio": 28.624801,
    "GEX_Call": 2900627.513,
    "GEX_Put": -389276.252,
    "GEX_Total": 2511351.261,
    "GEX_Ratio": 7.451334,
    "VEX_Call": 97276.735,
    "VEX_Put": 260495.233,
    "VEX_Total": 357771.968,
    "VEX_Ratio": 0.37343,
    "CEX_Call": 3779153.911,
    "CEX_Put": 11272743.668,
    "CEX_Total": 15051897.579,
    "CEX_Ratio": 0.335247
}