{
    "timestamp": "2025-08-18 12:51:37",
    "cum_gam": null,
    "cum_vec": 8200.0,
    "DEX_Call": 27.509,
    "DEX_Put": -40.414,
    "DEX_Total": -12.905,
    "DEX_Ratio": 0.68068,
    "GEX_Call": 2972433.039,
    "GEX_Put": -1456667.606,
    "GEX_Total": 1515765.433,
    "GEX_Ratio": 2.040571,
    "VEX_Call": -115414.674,
    "VEX_Put": 82003.564,
    "VEX_Total": -33411.11,
    "VEX_Ratio": -1.407435,
    "CEX_Call": -14557014.242,
    "CEX_Put": 9785450.042,
    "CEX_Total": -4771564.2,
    "CEX_Ratio": -1.487618
}