{
    "timestamp": "2025-10-30 10:57:50",
    "cum_gam": 6859.268727868153,
    "cum_vec": 6859.268727868153,
    "DEX_Call": 158.948,
    "DEX_Put": -93.981,
    "DEX_Total": 64.967,
    "DEX_Ratio": 1.691278,
    "GEX_Call": 1110004.593,
    "GEX_Put": -1542480.313,
    "GEX_Total": -432475.72,
    "GEX_Ratio": 0.719623,
    "VEX_Call": -97193.242,
    "VEX_Put": 200767.421,
    "VEX_Total": 103574.179,
    "VEX_Ratio": -0.484109,
    "CEX_Call": -4906605.189,
    "CEX_Put": 9536178.049,
    "CEX_Total": 4629572.86,
    "CEX_Ratio": -0.514525
}