{
    "timestamp": "2025-07-24 09:06:12",
    "cum_gam": null,
    "cum_vec": 8200.0,
    "DEX_Call": 206.795,
    "DEX_Put": -21.882,
    "DEX_Total": 184.913,
    "DEX_Ratio": 9.450462,
    "GEX_Call": 2590542.459,
    "GEX_Put": -791176.742,
    "GEX_Total": 1799365.717,
    "GEX_Ratio": 3.27429,
    "VEX_Call": -103420.56,
    "VEX_Put": 312826.595,
    "VEX_Total": 209406.035,
    "VEX_Ratio": -0.3306,
    "CEX_Call": -3874191.094,
    "CEX_Put": 10370938.026,
    "CEX_Total": 6496746.932,
    "CEX_Ratio": -0.373562
}