{
    "timestamp": "2025-11-06 11:30:39",
    "cum_gam": 6765.7887840808735,
    "cum_vec": 6765.7887840808735,
    "DEX_Call": 26.806,
    "DEX_Put": -201.31,
    "DEX_Total": -174.504,
    "DEX_Ratio": 0.133158,
    "GEX_Call": 287915.318,
    "GEX_Put": -1809651.275,
    "GEX_Total": -1521735.957,
    "GEX_Ratio": 0.1591,
    "VEX_Call": -150109.317,
    "VEX_Put": 149359.314,
    "VEX_Total": -750.003,
    "VEX_Ratio": -1.005021,
    "CEX_Call": -8983903.693,
    "CEX_Put": 8611559.407,
    "CEX_Total": -372344.286,
    "CEX_Ratio": -1.043238
}