{
    "timestamp": "2025-08-01 11:06:17",
    "cum_gam": 7928.778467908903,
    "cum_vec": 7928.778467908903,
    "DEX_Call": 65.73,
    "DEX_Put": -364.644,
    "DEX_Total": -298.914,
    "DEX_Ratio": 0.180258,
    "GEX_Call": 324250.198,
    "GEX_Put": -2355502.1,
    "GEX_Total": -2031251.902,
    "GEX_Ratio": 0.137657,
    "VEX_Call": -138990.091,
    "VEX_Put": 109212.942,
    "VEX_Total": -29777.149,
    "VEX_Ratio": -1.272652,
    "CEX_Call": -7868367.774,
    "CEX_Put": 5774874.598,
    "CEX_Total": -2093493.176,
    "CEX_Ratio": -1.362518
}