{
    "timestamp": "2025-07-24 06:52:30",
    "cum_gam": null,
    "cum_vec": 8200.0,
    "DEX_Call": 209.938,
    "DEX_Put": -26.962,
    "DEX_Total": 182.976,
    "DEX_Ratio": 7.78644,
    "GEX_Call": 2504745.581,
    "GEX_Put": -792004.451,
    "GEX_Total": 1712741.13,
    "GEX_Ratio": 3.16254,
    "VEX_Call": -170754.263,
    "VEX_Put": 331943.873,
    "VEX_Total": 161189.61,
    "VEX_Ratio": -0.514407,
    "CEX_Call": -4392404.698,
    "CEX_Put": 7654380.911,
    "CEX_Total": 3261976.213,
    "CEX_Ratio": -0.573842
}