{
    "timestamp": "2025-11-04 09:22:18",
    "cum_gam": 6819.77537522351,
    "cum_vec": 6819.77537522351,
    "DEX_Call": 43.173,
    "DEX_Put": -131.001,
    "DEX_Total": -87.828,
    "DEX_Ratio": 0.329562,
    "GEX_Call": 532031.522,
    "GEX_Put": -1577211.133,
    "GEX_Total": -1045179.611,
    "GEX_Ratio": 0.337324,
    "VEX_Call": -167061.235,
    "VEX_Put": 268674.248,
    "VEX_Total": 101613.013,
    "VEX_Ratio": -0.621798,
    "CEX_Call": -5629286.723,
    "CEX_Put": 8673174.549,
    "CEX_Total": 3043887.826,
    "CEX_Ratio": -0.649046
}