{
    "timestamp": "2025-09-10 09:54:47",
    "cum_gam": null,
    "cum_vec": null,
    "DEX_Call": 143.895,
    "DEX_Put": -41.976,
    "DEX_Total": 101.919,
    "DEX_Ratio": 3.42803,
    "GEX_Call": 2985742.107,
    "GEX_Put": -1229286.002,
    "GEX_Total": 1756456.105,
    "GEX_Ratio": 2.428843,
    "VEX_Call": -159324.682,
    "VEX_Put": 275562.568,
    "VEX_Total": 116237.886,
    "VEX_Ratio": -0.57818,
    "CEX_Call": -6648396.078,
    "CEX_Put": 10500075.258,
    "CEX_Total": 3851679.18,
    "CEX_Ratio": -0.633176
}