{
    "timestamp": "2025-09-02 07:05:01",
    "cum_gam": 6425.912362360726,
    "cum_vec": 8000.0,
    "DEX_Call": 43.619,
    "DEX_Put": -132.433,
    "DEX_Total": -88.814,
    "DEX_Ratio": 0.329367,
    "GEX_Call": 478616.219,
    "GEX_Put": -1573237.899,
    "GEX_Total": -1094621.68,
    "GEX_Ratio": 0.304224,
    "VEX_Call": -167042.532,
    "VEX_Put": 324001.336,
    "VEX_Total": 156958.804,
    "VEX_Ratio": -0.515561,
    "CEX_Call": -4080954.823,
    "CEX_Put": 7524761.058,
    "CEX_Total": 3443806.235,
    "CEX_Ratio": -0.542337
}