{
    "timestamp": "2025-06-26 07:14:57",
    "cum_gam": 6427.729218694256,
    "cum_vec": 6427.729218694256,
    "DEX_Call": 116.319,
    "DEX_Put": -20.658,
    "DEX_Total": 95.661,
    "DEX_Ratio": 5.6307,
    "GEX_Call": 1731895.378,
    "GEX_Put": -606025.647,
    "GEX_Total": 1125869.731,
    "GEX_Ratio": 2.857792,
    "VEX_Call": -116654.963,
    "VEX_Put": 293781.723,
    "VEX_Total": 177126.76,
    "VEX_Ratio": -0.39708,
    "CEX_Call": -3270196.607,
    "CEX_Put": 7459564.98,
    "CEX_Total": 4189368.373,
    "CEX_Ratio": -0.43839
}