{
    "timestamp": "2025-07-01 11:06:09",
    "cum_gam": 7317.64705882353,
    "cum_vec": 7317.64705882353,
    "DEX_Call": 52.951,
    "DEX_Put": -41.931,
    "DEX_Total": 11.02,
    "DEX_Ratio": 1.262813,
    "GEX_Call": 2424088.736,
    "GEX_Put": -1797229.28,
    "GEX_Total": 626859.456,
    "GEX_Ratio": 1.348792,
    "VEX_Call": -436292.633,
    "VEX_Put": 547521.471,
    "VEX_Total": 111228.838,
    "VEX_Ratio": -0.79685,
    "CEX_Call": -24750121.918,
    "CEX_Put": 30303942.016,
    "CEX_Total": 5553820.098,
    "CEX_Ratio": -0.816729
}