{
    "timestamp": "2025-09-22 09:53:59",
    "cum_gam": null,
    "cum_vec": 8400.0,
    "DEX_Call": 88.291,
    "DEX_Put": -29.519,
    "DEX_Total": 58.772,
    "DEX_Ratio": 2.990989,
    "GEX_Call": 2589667.083,
    "GEX_Put": -862252.549,
    "GEX_Total": 1727414.534,
    "GEX_Ratio": 3.003374,
    "VEX_Call": -147556.728,
    "VEX_Put": 339624.463,
    "VEX_Total": 192067.735,
    "VEX_Ratio": -0.43447,
    "CEX_Call": -5987045.552,
    "CEX_Put": 12714251.577,
    "CEX_Total": 6727206.025,
    "CEX_Ratio": -0.470892
}