{
    "timestamp": "2025-10-01 06:51:05",
    "cum_gam": 6580.804182846951,
    "cum_vec": 8600.0,
    "DEX_Call": 63.571,
    "DEX_Put": -63.964,
    "DEX_Total": -0.393,
    "DEX_Ratio": 0.993856,
    "GEX_Call": 574802.437,
    "GEX_Put": -669772.585,
    "GEX_Total": -94970.148,
    "GEX_Ratio": 0.858205,
    "VEX_Call": -122472.967,
    "VEX_Put": 276754.381,
    "VEX_Total": 154281.414,
    "VEX_Ratio": -0.442533,
    "CEX_Call": -736202.464,
    "CEX_Put": 1356065.478,
    "CEX_Total": 619863.014,
    "CEX_Ratio": -0.542896
}