{
    "timestamp": "2025-10-15 10:36:54",
    "cum_gam": 6577.455781885569,
    "cum_vec": 8200.0,
    "DEX_Call": 51.123,
    "DEX_Put": -96.775,
    "DEX_Total": -45.652,
    "DEX_Ratio": 0.528267,
    "GEX_Call": 428606.55,
    "GEX_Put": -585433.12,
    "GEX_Total": -156826.57,
    "GEX_Ratio": 0.732119,
    "VEX_Call": -162305.728,
    "VEX_Put": 270761.232,
    "VEX_Total": 108455.504,
    "VEX_Ratio": -0.599442,
    "CEX_Call": -1041803.619,
    "CEX_Put": 1534799.842,
    "CEX_Total": 492996.223,
    "CEX_Ratio": -0.678788
}