{
    "timestamp": "2025-10-31 07:22:36",
    "cum_gam": 6829.93783621145,
    "cum_vec": 6829.93783621145,
    "DEX_Call": 86.563,
    "DEX_Put": -143.116,
    "DEX_Total": -56.553,
    "DEX_Ratio": 0.604845,
    "GEX_Call": 593865.002,
    "GEX_Put": -940301.734,
    "GEX_Total": -346436.732,
    "GEX_Ratio": 0.631569,
    "VEX_Call": -136589.535,
    "VEX_Put": 311501.532,
    "VEX_Total": 174911.997,
    "VEX_Ratio": -0.438488,
    "CEX_Call": -371880.081,
    "CEX_Put": 489627.01,
    "CEX_Total": 117746.929,
    "CEX_Ratio": -0.759517
}