{
    "timestamp": "2025-07-09 07:46:09",
    "cum_gam": null,
    "cum_vec": 8000.0,
    "DEX_Call": 35.678,
    "DEX_Put": -25.291,
    "DEX_Total": 10.387,
    "DEX_Ratio": 1.410699,
    "GEX_Call": 407674.164,
    "GEX_Put": -290577.238,
    "GEX_Total": 117096.926,
    "GEX_Ratio": 1.40298,
    "VEX_Call": -90918.118,
    "VEX_Put": 141096.868,
    "VEX_Total": 50178.75,
    "VEX_Ratio": -0.644367,
    "CEX_Call": -590695.812,
    "CEX_Put": 772477.204,
    "CEX_Total": 181781.392,
    "CEX_Ratio": -0.764677
}