{
    "timestamp": "2025-07-30 12:04:49",
    "cum_gam": null,
    "cum_vec": null,
    "DEX_Call": 465.586,
    "DEX_Put": -142.27,
    "DEX_Total": 323.316,
    "DEX_Ratio": 3.272552,
    "GEX_Call": 1177887.65,
    "GEX_Put": -940305.665,
    "GEX_Total": 237581.985,
    "GEX_Ratio": 1.252665,
    "VEX_Call": -269942.609,
    "VEX_Put": 405577.284,
    "VEX_Total": 135634.675,
    "VEX_Ratio": -0.665576,
    "CEX_Call": -1978022.039,
    "CEX_Put": 2548532.761,
    "CEX_Total": 570510.722,
    "CEX_Ratio": -0.776141
}