{
    "timestamp": "2025-09-10 09:45:53",
    "cum_gam": null,
    "cum_vec": 8200.0,
    "DEX_Call": 86.402,
    "DEX_Put": -27.17,
    "DEX_Total": 59.232,
    "DEX_Ratio": 3.180052,
    "GEX_Call": 763401.402,
    "GEX_Put": -392731.552,
    "GEX_Total": 370669.85,
    "GEX_Ratio": 1.943825,
    "VEX_Call": -67020.16,
    "VEX_Put": 282803.561,
    "VEX_Total": 215783.401,
    "VEX_Ratio": -0.236985,
    "CEX_Call": -516577.196,
    "CEX_Put": 1615204.552,
    "CEX_Total": 1098627.356,
    "CEX_Ratio": -0.319822
}