{
    "timestamp": "2025-10-28 07:12:13",
    "cum_gam": null,
    "cum_vec": 8400.0,
    "DEX_Call": 226.103,
    "DEX_Put": -33.071,
    "DEX_Total": 193.032,
    "DEX_Ratio": 6.836896,
    "GEX_Call": 1399409.366,
    "GEX_Put": -453161.989,
    "GEX_Total": 946247.377,
    "GEX_Ratio": 3.0881,
    "VEX_Call": -12191.672,
    "VEX_Put": 420416.344,
    "VEX_Total": 408224.672,
    "VEX_Ratio": -0.028999,
    "CEX_Call": -281592.729,
    "CEX_Put": 2100899.862,
    "CEX_Total": 1819307.133,
    "CEX_Ratio": -0.134034
}