{
    "timestamp": "2025-11-17 12:21:05",
    "cum_gam": 6738.998281772296,
    "cum_vec": 8800.0,
    "DEX_Call": 11.026,
    "DEX_Put": -162.032,
    "DEX_Total": -151.006,
    "DEX_Ratio": 0.068048,
    "GEX_Call": 114271.671,
    "GEX_Put": -827172.426,
    "GEX_Total": -712900.755,
    "GEX_Ratio": 0.138147,
    "VEX_Call": -89281.237,
    "VEX_Put": 202928.708,
    "VEX_Total": 113647.471,
    "VEX_Ratio": -0.439964,
    "CEX_Call": -587631.924,
    "CEX_Put": 1165841.848,
    "CEX_Total": 578209.924,
    "CEX_Ratio": -0.504041
}