{
    "timestamp": "2025-09-25 09:42:27",
    "cum_gam": 6601.784509741619,
    "cum_vec": 8123.605150214592,
    "DEX_Call": 193.164,
    "DEX_Put": -191.398,
    "DEX_Total": 1.766,
    "DEX_Ratio": 1.009227,
    "GEX_Call": 1057650.147,
    "GEX_Put": -1807725.651,
    "GEX_Total": -750075.504,
    "GEX_Ratio": 0.585072,
    "VEX_Call": -234601.947,
    "VEX_Put": 546543.338,
    "VEX_Total": 311941.391,
    "VEX_Ratio": -0.429247,
    "CEX_Call": -1537891.36,
    "CEX_Put": 2915443.662,
    "CEX_Total": 1377552.302,
    "CEX_Ratio": -0.527498
}