{
    "timestamp": "2025-10-31 08:13:38",
    "cum_gam": 6828.304986482769,
    "cum_vec": 6828.304986482769,
    "DEX_Call": 96.102,
    "DEX_Put": -122.32,
    "DEX_Total": -26.218,
    "DEX_Ratio": 0.785661,
    "GEX_Call": 649474.94,
    "GEX_Put": -931660.479,
    "GEX_Total": -282185.539,
    "GEX_Ratio": 0.697115,
    "VEX_Call": -100639.175,
    "VEX_Put": 353012.654,
    "VEX_Total": 252373.479,
    "VEX_Ratio": -0.285087,
    "CEX_Call": -308863.094,
    "CEX_Put": 581961.699,
    "CEX_Total": 273098.605,
    "CEX_Ratio": -0.530728
}