{
    "timestamp": "2025-07-22 12:11:49",
    "cum_gam": null,
    "cum_vec": null,
    "DEX_Call": 75.543,
    "DEX_Put": -28.421,
    "DEX_Total": 47.122,
    "DEX_Ratio": 2.657999,
    "GEX_Call": 709396.008,
    "GEX_Put": -506585.231,
    "GEX_Total": 202810.777,
    "GEX_Ratio": 1.400349,
    "VEX_Call": -57494.017,
    "VEX_Put": 167702.513,
    "VEX_Total": 110208.496,
    "VEX_Ratio": -0.342833,
    "CEX_Call": -496476.022,
    "CEX_Put": 1045763.853,
    "CEX_Total": 549287.831,
    "CEX_Ratio": -0.47475
}