{
    "timestamp": "2025-06-30 12:00:34",
    "cum_gam": null,
    "cum_vec": 8000.0,
    "DEX_Call": 163.524,
    "DEX_Put": -12.965,
    "DEX_Total": 150.559,
    "DEX_Ratio": 12.612727,
    "GEX_Call": 643926.7,
    "GEX_Put": -240467.987,
    "GEX_Total": 403458.713,
    "GEX_Ratio": 2.677806,
    "VEX_Call": 60646.378,
    "VEX_Put": 177777.553,
    "VEX_Total": 238423.931,
    "VEX_Ratio": 0.341136,
    "CEX_Call": 311201.919,
    "CEX_Put": 1169564.884,
    "CEX_Total": 1480766.803,
    "CEX_Ratio": 0.266084
}