{
    "timestamp": "2025-07-30 08:46:26",
    "cum_gam": null,
    "cum_vec": 6920.915073255525,
    "DEX_Call": 287.137,
    "DEX_Put": -114.064,
    "DEX_Total": 173.073,
    "DEX_Ratio": 2.517332,
    "GEX_Call": 1499365.932,
    "GEX_Put": -823699.261,
    "GEX_Total": 675666.671,
    "GEX_Ratio": 1.820283,
    "VEX_Call": -373291.699,
    "VEX_Put": 492300.669,
    "VEX_Total": 119008.97,
    "VEX_Ratio": -0.75826,
    "CEX_Call": -2425959.826,
    "CEX_Put": 2761794.713,
    "CEX_Total": 335834.887,
    "CEX_Ratio": -0.8784
}