{
    "timestamp": "2025-10-17 06:54:15",
    "cum_gam": 8663.695937090433,
    "cum_vec": 8663.695937090433,
    "DEX_Call": 997.904,
    "DEX_Put": -1419.945,
    "DEX_Total": -422.041,
    "DEX_Ratio": 0.702777,
    "GEX_Call": 3726044.051,
    "GEX_Put": -5159825.567,
    "GEX_Total": -1433781.516,
    "GEX_Ratio": 0.722126,
    "VEX_Call": -2287021.697,
    "VEX_Put": 6336737.872,
    "VEX_Total": 4049716.175,
    "VEX_Ratio": -0.360915,
    "CEX_Call": -10770630.259,
    "CEX_Put": 21220319.799,
    "CEX_Total": 10449689.54,
    "CEX_Ratio": -0.507562
}