{
    "timestamp": "2025-07-10 07:12:04",
    "cum_gam": null,
    "cum_vec": 7214.492238571414,
    "DEX_Call": 3173.884,
    "DEX_Put": -652.885,
    "DEX_Total": 2520.999,
    "DEX_Ratio": 4.861322,
    "GEX_Call": 7636725.944,
    "GEX_Put": -4620634.872,
    "GEX_Total": 3016091.072,
    "GEX_Ratio": 1.652744,
    "VEX_Call": 343962.038,
    "VEX_Put": 5480741.738,
    "VEX_Total": 5824703.776,
    "VEX_Ratio": 0.062758,
    "CEX_Call": -4450154.947,
    "CEX_Put": 12844532.172,
    "CEX_Total": 8394377.225,
    "CEX_Ratio": -0.346463
}