{
    "timestamp": "2025-10-22 08:03:29",
    "cum_gam": 8770.680628272252,
    "cum_vec": 8770.680628272252,
    "DEX_Call": 1101.685,
    "DEX_Put": -690.716,
    "DEX_Total": 410.969,
    "DEX_Ratio": 1.59499,
    "GEX_Call": 5722286.942,
    "GEX_Put": -5637307.859,
    "GEX_Total": 84979.083,
    "GEX_Ratio": 1.015074,
    "VEX_Call": -1198188.614,
    "VEX_Put": 4796531.801,
    "VEX_Total": 3598343.187,
    "VEX_Ratio": -0.249803,
    "CEX_Call": -9696842.505,
    "CEX_Put": 20290954.063,
    "CEX_Total": 10594111.558,
    "CEX_Ratio": -0.47789
}