{
    "timestamp": "2025-09-03 09:56:20",
    "cum_gam": 7009.131277765844,
    "cum_vec": 7468.9943122060695,
    "DEX_Call": 6902.116,
    "DEX_Put": -2941.544,
    "DEX_Total": 3960.572,
    "DEX_Ratio": 2.346426,
    "GEX_Call": 13247166.564,
    "GEX_Put": -11377241.895,
    "GEX_Total": 1869924.669,
    "GEX_Ratio": 1.164357,
    "VEX_Call": 1327564.698,
    "VEX_Put": 16530889.786,
    "VEX_Total": 17858454.484,
    "VEX_Ratio": 0.080308,
    "CEX_Call": -13207620.286,
    "CEX_Put": 25056396.451,
    "CEX_Total": 11848776.165,
    "CEX_Ratio": -0.527116
}