{
    "timestamp": "2025-10-13 09:39:21",
    "cum_gam": 6437.931460026153,
    "cum_vec": 6437.931460026153,
    "DEX_Call": 3080.095,
    "DEX_Put": -2180.632,
    "DEX_Total": 899.463,
    "DEX_Ratio": 1.412478,
    "GEX_Call": 7932951.408,
    "GEX_Put": -8962772.326,
    "GEX_Total": -1029820.918,
    "GEX_Ratio": 0.8851,
    "VEX_Call": -2030546.003,
    "VEX_Put": 8887685.446,
    "VEX_Total": 6857139.443,
    "VEX_Ratio": -0.228467,
    "CEX_Call": -7092635.817,
    "CEX_Put": 21235522.953,
    "CEX_Total": 14142887.136,
    "CEX_Ratio": -0.333999
}