{
    "timestamp": "2025-10-06 06:58:56",
    "cum_gam": 8212.5,
    "cum_vec": 8603.880910983751,
    "DEX_Call": 3692.4,
    "DEX_Put": -1430.37,
    "DEX_Total": 2262.03,
    "DEX_Ratio": 2.58143,
    "GEX_Call": 9888631.363,
    "GEX_Put": -7378159.645,
    "GEX_Total": 2510471.718,
    "GEX_Ratio": 1.340257,
    "VEX_Call": -644634.182,
    "VEX_Put": 10822257.82,
    "VEX_Total": 10177623.638,
    "VEX_Ratio": -0.059566,
    "CEX_Call": -7343394.031,
    "CEX_Put": 18539250.605,
    "CEX_Total": 11195856.574,
    "CEX_Ratio": -0.3961
}