{
    "timestamp": "2025-07-18 11:23:28",
    "cum_gam": 8598.976819407007,
    "cum_vec": 8598.976819407007,
    "DEX_Call": 1031.328,
    "DEX_Put": -346.065,
    "DEX_Total": 685.263,
    "DEX_Ratio": 2.980157,
    "GEX_Call": 7676116.585,
    "GEX_Put": -4838107.013,
    "GEX_Total": 2838009.572,
    "GEX_Ratio": 1.586595,
    "VEX_Call": -908702.124,
    "VEX_Put": 2243177.037,
    "VEX_Total": 1334474.913,
    "VEX_Ratio": -0.405096,
    "CEX_Call": -7048278.168,
    "CEX_Put": 9827695.691,
    "CEX_Total": 2779417.523,
    "CEX_Ratio": -0.717185
}