{
    "timestamp": "2025-07-17 11:28:36",
    "cum_gam": 10399.402427637722,
    "cum_vec": 10399.402427637722,
    "DEX_Call": 2825.243,
    "DEX_Put": -400.006,
    "DEX_Total": 2425.237,
    "DEX_Ratio": 7.063002,
    "GEX_Call": 11087260.727,
    "GEX_Put": -4928330.586,
    "GEX_Total": 6158930.141,
    "GEX_Ratio": 2.249699,
    "VEX_Call": 78314.047,
    "VEX_Put": 3502754.859,
    "VEX_Total": 3581068.906,
    "VEX_Ratio": 0.022358,
    "CEX_Call": 2023549.625,
    "CEX_Put": 19523411.285,
    "CEX_Total": 21546960.91,
    "CEX_Ratio": 0.103647
}