{
    "timestamp": "2026-07-21 12:19:36",
    "cum_gam": null,
    "cum_vec": null,
    "DEX_Call": 869.805,
    "DEX_Put": -925.941,
    "DEX_Total": -56.136,
    "DEX_Ratio": 0.939374,
    "GEX_Call": 7559949.923,
    "GEX_Put": -5678858.648,
    "GEX_Total": 1881091.275,
    "GEX_Ratio": 1.331245,
    "VEX_Call": -2766405.594,
    "VEX_Put": 4278974.625,
    "VEX_Total": 1512569.031,
    "VEX_Ratio": -0.646511,
    "CEX_Call": -12751906.053,
    "CEX_Put": 14117930.962,
    "CEX_Total": 1366024.909,
    "CEX_Ratio": -0.903242
}