{
    "timestamp": "2025-10-21 06:39:56",
    "cum_gam": 8796.873255164712,
    "cum_vec": 8796.873255164712,
    "DEX_Call": 1221.812,
    "DEX_Put": -627.566,
    "DEX_Total": 594.246,
    "DEX_Ratio": 1.946906,
    "GEX_Call": 6738364.995,
    "GEX_Put": -4338380.879,
    "GEX_Total": 2399984.116,
    "GEX_Ratio": 1.553198,
    "VEX_Call": -1282949.829,
    "VEX_Put": 5167142.406,
    "VEX_Total": 3884192.577,
    "VEX_Ratio": -0.24829,
    "CEX_Call": -9681257.287,
    "CEX_Put": 17042109.336,
    "CEX_Total": 7360852.049,
    "CEX_Ratio": -0.568079
}