{
    "timestamp": "2025-11-20 10:50:01",
    "cum_gam": 6602.824536226551,
    "cum_vec": 6602.824536226551,
    "DEX_Call": 2191.758,
    "DEX_Put": -2503.485,
    "DEX_Total": -311.727,
    "DEX_Ratio": 0.875483,
    "GEX_Call": 3299262.029,
    "GEX_Put": -6640318.513,
    "GEX_Total": -3341056.484,
    "GEX_Ratio": 0.496853,
    "VEX_Call": -2298227.496,
    "VEX_Put": 4085294.25,
    "VEX_Total": 1787066.754,
    "VEX_Ratio": -0.562561,
    "CEX_Call": -20599211.668,
    "CEX_Put": 31276412.257,
    "CEX_Total": 10677200.589,
    "CEX_Ratio": -0.658618
}