{
    "timestamp": "2025-07-01 07:51:05",
    "cum_gam": 7006.391485788361,
    "cum_vec": 7214.400788155907,
    "DEX_Call": 2929.053,
    "DEX_Put": -1037.355,
    "DEX_Total": 1891.698,
    "DEX_Ratio": 2.823578,
    "GEX_Call": 8125119.429,
    "GEX_Put": -7933675.866,
    "GEX_Total": 191443.563,
    "GEX_Ratio": 1.02413,
    "VEX_Call": 289592.663,
    "VEX_Put": 8461475.521,
    "VEX_Total": 8751068.184,
    "VEX_Ratio": 0.034225,
    "CEX_Call": -11749678.997,
    "CEX_Put": 25378366.441,
    "CEX_Total": 13628687.444,
    "CEX_Ratio": -0.46298
}