{
    "timestamp": "2025-06-27 08:30:04",
    "cum_gam": 6326.1499776404335,
    "cum_vec": 6402.320940558448,
    "DEX_Call": 445.613,
    "DEX_Put": -110.114,
    "DEX_Total": 335.499,
    "DEX_Ratio": 4.046833,
    "GEX_Call": 5502654.467,
    "GEX_Put": -1171177.428,
    "GEX_Total": 4331477.039,
    "GEX_Ratio": 4.698395,
    "VEX_Call": -192216.862,
    "VEX_Put": 1116238.544,
    "VEX_Total": 924021.682,
    "VEX_Ratio": -0.172201,
    "CEX_Call": -2096258.675,
    "CEX_Put": 15194601.575,
    "CEX_Total": 13098342.9,
    "CEX_Ratio": -0.137961
}