{
    "timestamp": "2025-07-02 11:58:39",
    "cum_gam": 7023.614881369822,
    "cum_vec": 7121.5092002019,
    "DEX_Call": 2980.471,
    "DEX_Put": -730.638,
    "DEX_Total": 2249.833,
    "DEX_Ratio": 4.079272,
    "GEX_Call": 8675771.937,
    "GEX_Put": -3877804.662,
    "GEX_Total": 4797967.275,
    "GEX_Ratio": 2.23729,
    "VEX_Call": 926718.801,
    "VEX_Put": 7211004.736,
    "VEX_Total": 8137723.537,
    "VEX_Ratio": 0.128515,
    "CEX_Call": -10583648.423,
    "CEX_Put": 17247481.724,
    "CEX_Total": 6663833.301,
    "CEX_Ratio": -0.613634
}