{
    "timestamp": "2025-09-09 10:38:27",
    "cum_gam": 7009.025731182982,
    "cum_vec": 7499.910905110023,
    "DEX_Call": 4921.546,
    "DEX_Put": -1797.346,
    "DEX_Total": 3124.2,
    "DEX_Ratio": 2.73823,
    "GEX_Call": 14855617.042,
    "GEX_Put": -10195215.539,
    "GEX_Total": 4660401.503,
    "GEX_Ratio": 1.457117,
    "VEX_Call": 1960191.321,
    "VEX_Put": 14492821.407,
    "VEX_Total": 16453012.728,
    "VEX_Ratio": 0.135253,
    "CEX_Call": -5625388.183,
    "CEX_Put": 22423835.48,
    "CEX_Total": 16798447.297,
    "CEX_Ratio": -0.250866
}