{
    "timestamp": "2025-10-09 10:44:12",
    "cum_gam": 6712.676002346326,
    "cum_vec": 9093.886310795673,
    "DEX_Call": 2760.764,
    "DEX_Put": -1774.601,
    "DEX_Total": 986.163,
    "DEX_Ratio": 1.55571,
    "GEX_Call": 9813038.748,
    "GEX_Put": -13143455.205,
    "GEX_Total": -3330416.457,
    "GEX_Ratio": 0.74661,
    "VEX_Call": -1346277.374,
    "VEX_Put": 10790337.11,
    "VEX_Total": 9444059.736,
    "VEX_Ratio": -0.124767,
    "CEX_Call": -17751193.706,
    "CEX_Put": 32063929.018,
    "CEX_Total": 14312735.312,
    "CEX_Ratio": -0.553619
}