{
    "timestamp": "2025-09-10 08:46:43",
    "cum_gam": 7008.6832323196895,
    "cum_vec": 7483.508210141089,
    "DEX_Call": 5296.357,
    "DEX_Put": -1421.716,
    "DEX_Total": 3874.641,
    "DEX_Ratio": 3.725327,
    "GEX_Call": 15582825.028,
    "GEX_Put": -8569178.816,
    "GEX_Total": 7013646.212,
    "GEX_Ratio": 1.818474,
    "VEX_Call": 2990018.132,
    "VEX_Put": 14500742.604,
    "VEX_Total": 17490760.736,
    "VEX_Ratio": 0.206198,
    "CEX_Call": -4048771.143,
    "CEX_Put": 21886588.696,
    "CEX_Total": 17837817.553,
    "CEX_Ratio": -0.184989
}