{
    "timestamp": "2025-10-01 06:30:30",
    "cum_gam": 8352.213837621603,
    "cum_vec": 8503.079035104922,
    "DEX_Call": 317.269,
    "DEX_Put": -344.674,
    "DEX_Total": -27.405,
    "DEX_Ratio": 0.92049,
    "GEX_Call": 5060818.396,
    "GEX_Put": -3225732.239,
    "GEX_Total": 1835086.157,
    "GEX_Ratio": 1.56889,
    "VEX_Call": -887017.901,
    "VEX_Put": 2926235.744,
    "VEX_Total": 2039217.843,
    "VEX_Ratio": -0.303126,
    "CEX_Call": -12879627.062,
    "CEX_Put": 31027957.667,
    "CEX_Total": 18148330.605,
    "CEX_Ratio": -0.415097
}