{
    "timestamp": "2025-08-12 10:34:30",
    "cum_gam": 7009.6754858997265,
    "cum_vec": 7515.423134702053,
    "DEX_Call": 1682.014,
    "DEX_Put": -310.753,
    "DEX_Total": 1371.261,
    "DEX_Ratio": 5.412704,
    "GEX_Call": 8699433.416,
    "GEX_Put": -2612838.994,
    "GEX_Total": 6086594.422,
    "GEX_Ratio": 3.329495,
    "VEX_Call": 105072.322,
    "VEX_Put": 3069202.589,
    "VEX_Total": 3174274.911,
    "VEX_Ratio": 0.034234,
    "CEX_Call": -544739.81,
    "CEX_Put": 19778164.623,
    "CEX_Total": 19233424.813,
    "CEX_Ratio": -0.027542
}