{
    "timestamp": "2025-10-16 09:03:03",
    "cum_gam": 6382.678698294268,
    "cum_vec": 6382.678698294268,
    "DEX_Call": 2929.551,
    "DEX_Put": -795.55,
    "DEX_Total": 2134.001,
    "DEX_Ratio": 3.682422,
    "GEX_Call": 6176214.053,
    "GEX_Put": -6201944.839,
    "GEX_Total": -25730.786,
    "GEX_Ratio": 0.995851,
    "VEX_Call": 166292.478,
    "VEX_Put": 3456724.569,
    "VEX_Total": 3623017.047,
    "VEX_Ratio": 0.048107,
    "CEX_Call": -7340850.345,
    "CEX_Put": 32561415.223,
    "CEX_Total": 25220564.878,
    "CEX_Ratio": -0.225446
}