{
    "timestamp": "2025-08-15 11:50:01",
    "cum_gam": null,
    "cum_vec": null,
    "DEX_Call": 418.727,
    "DEX_Put": -54.858,
    "DEX_Total": 363.869,
    "DEX_Ratio": 7.632925,
    "GEX_Call": 3114226.091,
    "GEX_Put": -2128204.55,
    "GEX_Total": 986021.541,
    "GEX_Ratio": 1.463311,
    "VEX_Call": 51416.169,
    "VEX_Put": 329310.204,
    "VEX_Total": 380726.373,
    "VEX_Ratio": 0.156133,
    "CEX_Call": 3133044.472,
    "CEX_Put": 22850011.594,
    "CEX_Total": 25983056.066,
    "CEX_Ratio": 0.137113
}