{
    "timestamp": "2025-07-22 06:57:58",
    "cum_gam": 6255.255404722191,
    "cum_vec": 6255.255404722191,
    "DEX_Call": 314.01,
    "DEX_Put": -252.508,
    "DEX_Total": 61.502,
    "DEX_Ratio": 1.243565,
    "GEX_Call": 2448391.887,
    "GEX_Put": -3326265.575,
    "GEX_Total": -877873.688,
    "GEX_Ratio": 0.736078,
    "VEX_Call": -631192.659,
    "VEX_Put": 1215851.247,
    "VEX_Total": 584658.588,
    "VEX_Ratio": -0.519136,
    "CEX_Call": -5559248.437,
    "CEX_Put": 10357299.597,
    "CEX_Total": 4798051.16,
    "CEX_Ratio": -0.536747
}