{
    "timestamp": "2025-09-04 08:59:51",
    "cum_gam": 8195.258620689656,
    "cum_vec": 8195.258620689656,
    "DEX_Call": 390.956,
    "DEX_Put": -127.264,
    "DEX_Total": 263.692,
    "DEX_Ratio": 3.072008,
    "GEX_Call": 6550309.743,
    "GEX_Put": -2040592.105,
    "GEX_Total": 4509717.638,
    "GEX_Ratio": 3.210004,
    "VEX_Call": -350104.066,
    "VEX_Put": 1157284.948,
    "VEX_Total": 807180.882,
    "VEX_Ratio": -0.302522,
    "CEX_Call": -8023154.641,
    "CEX_Put": 17740335.984,
    "CEX_Total": 9717181.343,
    "CEX_Ratio": -0.452255
}