{
    "timestamp": "2025-07-22 07:18:20",
    "cum_gam": 6251.063815719747,
    "cum_vec": 7352.11970074813,
    "DEX_Call": 248.367,
    "DEX_Put": -295.451,
    "DEX_Total": -47.084,
    "DEX_Ratio": 0.840637,
    "GEX_Call": 2634748.285,
    "GEX_Put": -3423675.496,
    "GEX_Total": -788927.211,
    "GEX_Ratio": 0.769567,
    "VEX_Call": -721595.483,
    "VEX_Put": 1111718.676,
    "VEX_Total": 390123.193,
    "VEX_Ratio": -0.649081,
    "CEX_Call": -7432040.617,
    "CEX_Put": 7979376.002,
    "CEX_Total": 547335.385,
    "CEX_Ratio": -0.931406
}