{
    "timestamp": "2025-11-18 11:42:06",
    "cum_gam": 10720.87912087912,
    "cum_vec": 10720.87912087912,
    "DEX_Call": 2033.144,
    "DEX_Put": -1471.966,
    "DEX_Total": 561.178,
    "DEX_Ratio": 1.381244,
    "GEX_Call": 3453097.685,
    "GEX_Put": -6196935.864,
    "GEX_Total": -2743838.179,
    "GEX_Ratio": 0.557227,
    "VEX_Call": -1143050.644,
    "VEX_Put": 3687015.541,
    "VEX_Total": 2543964.897,
    "VEX_Ratio": -0.310021,
    "CEX_Call": -14377681.995,
    "CEX_Put": 31486865.115,
    "CEX_Total": 17109183.12,
    "CEX_Ratio": -0.456625
}