{
    "timestamp": "2025-09-23 07:36:19",
    "cum_gam": null,
    "cum_vec": null,
    "DEX_Call": 614.557,
    "DEX_Put": -181.71,
    "DEX_Total": 432.847,
    "DEX_Ratio": 3.382076,
    "GEX_Call": 5413342.39,
    "GEX_Put": -3087927.095,
    "GEX_Total": 2325415.295,
    "GEX_Ratio": 1.753067,
    "VEX_Call": -608553.821,
    "VEX_Put": 1727031.377,
    "VEX_Total": 1118477.556,
    "VEX_Ratio": -0.35237,
    "CEX_Call": -10492862.734,
    "CEX_Put": 12576256.915,
    "CEX_Total": 2083394.181,
    "CEX_Ratio": -0.834339
}