{
    "timestamp": "2025-11-04 10:09:27",
    "cum_gam": 6793.750901622263,
    "cum_vec": 6793.750901622263,
    "DEX_Call": 324.072,
    "DEX_Put": -501.045,
    "DEX_Total": -176.973,
    "DEX_Ratio": 0.646792,
    "GEX_Call": 2020292.332,
    "GEX_Put": -3880396.891,
    "GEX_Total": -1860104.559,
    "GEX_Ratio": 0.520641,
    "VEX_Call": -847144.9,
    "VEX_Put": 1502562.021,
    "VEX_Total": 655417.121,
    "VEX_Ratio": -0.5638,
    "CEX_Call": -7623813.498,
    "CEX_Put": 14513011.534,
    "CEX_Total": 6889198.036,
    "CEX_Ratio": -0.525309
}