{
    "timestamp": "2025-08-13 11:26:14",
    "cum_gam": 7009.567784272839,
    "cum_vec": 9126.383114806524,
    "DEX_Call": 1576.404,
    "DEX_Put": -273.876,
    "DEX_Total": 1302.528,
    "DEX_Ratio": 5.755904,
    "GEX_Call": 9673827.853,
    "GEX_Put": -2815801.229,
    "GEX_Total": 6858026.624,
    "GEX_Ratio": 3.435551,
    "VEX_Call": -24270.432,
    "VEX_Put": 2419983.423,
    "VEX_Total": 2395712.991,
    "VEX_Ratio": -0.010029,
    "CEX_Call": -8246493.915,
    "CEX_Put": 19327848.503,
    "CEX_Total": 11081354.588,
    "CEX_Ratio": -0.426664
}