{
    "timestamp": "2025-08-22 08:49:00",
    "cum_gam": 8196.74355495251,
    "cum_vec": 8196.74355495251,
    "DEX_Call": 451.38,
    "DEX_Put": -40.818,
    "DEX_Total": 410.562,
    "DEX_Ratio": 11.058357,
    "GEX_Call": 3807168.633,
    "GEX_Put": -847139.997,
    "GEX_Total": 2960028.636,
    "GEX_Ratio": 4.494143,
    "VEX_Call": 64684.095,
    "VEX_Put": 547712.633,
    "VEX_Total": 612396.728,
    "VEX_Ratio": 0.118099,
    "CEX_Call": 1430689.869,
    "CEX_Put": 17018123.091,
    "CEX_Total": 18448812.96,
    "CEX_Ratio": 0.084069
}