{
    "timestamp": "2025-10-14 09:49:18",
    "cum_gam": 7003.419999714753,
    "cum_vec": 9197.110228887908,
    "DEX_Call": 2539.043,
    "DEX_Put": -1335.867,
    "DEX_Total": 1203.176,
    "DEX_Ratio": 1.900671,
    "GEX_Call": 7274043.212,
    "GEX_Put": -6372993.816,
    "GEX_Total": 901049.396,
    "GEX_Ratio": 1.141386,
    "VEX_Call": -832444.123,
    "VEX_Put": 4848657.381,
    "VEX_Total": 4016213.258,
    "VEX_Ratio": -0.171685,
    "CEX_Call": -12658585.391,
    "CEX_Put": 25537347.723,
    "CEX_Total": 12878762.332,
    "CEX_Ratio": -0.495689
}