{
    "timestamp": "2025-11-18 10:13:29",
    "cum_gam": 6670.951142184734,
    "cum_vec": 6670.951142184734,
    "DEX_Call": 1672.838,
    "DEX_Put": -2246.532,
    "DEX_Total": -573.694,
    "DEX_Ratio": 0.744631,
    "GEX_Call": 2687027.0,
    "GEX_Put": -6272999.975,
    "GEX_Total": -3585972.975,
    "GEX_Ratio": 0.428348,
    "VEX_Call": -1463281.847,
    "VEX_Put": 2826967.923,
    "VEX_Total": 1363686.076,
    "VEX_Ratio": -0.517615,
    "CEX_Call": -11581605.87,
    "CEX_Put": 12023867.502,
    "CEX_Total": 442261.632,
    "CEX_Ratio": -0.963218
}