{
    "timestamp": "2025-07-30 11:56:20",
    "cum_gam": 6247.782628708668,
    "cum_vec": 6901.505503993093,
    "DEX_Call": 508.564,
    "DEX_Put": -356.451,
    "DEX_Total": 152.113,
    "DEX_Ratio": 1.426743,
    "GEX_Call": 3411438.974,
    "GEX_Put": -3678759.016,
    "GEX_Total": -267320.042,
    "GEX_Ratio": 0.927334,
    "VEX_Call": -803779.341,
    "VEX_Put": 1451531.254,
    "VEX_Total": 647751.913,
    "VEX_Ratio": -0.553746,
    "CEX_Call": -14740383.191,
    "CEX_Put": 27342095.549,
    "CEX_Total": 12601712.358,
    "CEX_Ratio": -0.539109
}