{
    "timestamp": "2025-08-25 07:20:54",
    "cum_gam": null,
    "cum_vec": 7545.002160763279,
    "DEX_Call": 6534.419,
    "DEX_Put": -3209.544,
    "DEX_Total": 3324.875,
    "DEX_Ratio": 2.035934,
    "GEX_Call": 13943889.163,
    "GEX_Put": -11334476.901,
    "GEX_Total": 2609412.262,
    "GEX_Ratio": 1.230219,
    "VEX_Call": 17271.079,
    "VEX_Put": 26645288.99,
    "VEX_Total": 26662560.069,
    "VEX_Ratio": 0.000648,
    "CEX_Call": -10296447.894,
    "CEX_Put": 15189282.136,
    "CEX_Total": 4892834.242,
    "CEX_Ratio": -0.677876
}