{
    "timestamp": "2025-07-31 07:30:01",
    "cum_gam": null,
    "cum_vec": 7536.830600522738,
    "DEX_Call": 9270.584,
    "DEX_Put": -3357.347,
    "DEX_Total": 5913.237,
    "DEX_Ratio": 2.761283,
    "GEX_Call": 15168431.211,
    "GEX_Put": -9725802.102,
    "GEX_Total": 5442629.109,
    "GEX_Ratio": 1.559607,
    "VEX_Call": 4866772.534,
    "VEX_Put": 29704397.011,
    "VEX_Total": 34571169.545,
    "VEX_Ratio": 0.16384,
    "CEX_Call": -6121108.253,
    "CEX_Put": 20045849.04,
    "CEX_Total": 13924740.787,
    "CEX_Ratio": -0.305355
}