{
    "timestamp": "2025-11-18 12:06:12",
    "cum_gam": 6554.944312586696,
    "cum_vec": 7986.2895762530625,
    "DEX_Call": 11415.276,
    "DEX_Put": -8887.454,
    "DEX_Total": 2527.822,
    "DEX_Ratio": 1.284426,
    "GEX_Call": 12627382.475,
    "GEX_Put": -16904797.709,
    "GEX_Total": -4277415.234,
    "GEX_Ratio": 0.74697,
    "VEX_Call": -5750047.207,
    "VEX_Put": 30170876.969,
    "VEX_Total": 24420829.762,
    "VEX_Ratio": -0.190583,
    "CEX_Call": -18674043.299,
    "CEX_Put": 31984750.834,
    "CEX_Total": 13310707.535,
    "CEX_Ratio": -0.583842
}