{
    "timestamp": "2025-09-29 10:06:07",
    "cum_gam": null,
    "cum_vec": 7966.654025316093,
    "DEX_Call": 8570.42,
    "DEX_Put": -3428.045,
    "DEX_Total": 5142.375,
    "DEX_Ratio": 2.50009,
    "GEX_Call": 14565869.127,
    "GEX_Put": -11199464.148,
    "GEX_Total": 3366404.979,
    "GEX_Ratio": 1.300586,
    "VEX_Call": -464967.776,
    "VEX_Put": 27511365.894,
    "VEX_Total": 27046398.118,
    "VEX_Ratio": -0.016901,
    "CEX_Call": -13524048.318,
    "CEX_Put": 24463887.596,
    "CEX_Total": 10939839.278,
    "CEX_Ratio": -0.552817
}