{
    "timestamp": "2025-08-01 12:17:23",
    "cum_gam": 7005.4970628073615,
    "cum_vec": 7482.99673004315,
    "DEX_Call": 7591.668,
    "DEX_Put": -6387.139,
    "DEX_Total": 1204.529,
    "DEX_Ratio": 1.188587,
    "GEX_Call": 9429133.449,
    "GEX_Put": -13614369.289,
    "GEX_Total": -4185235.84,
    "GEX_Ratio": 0.692587,
    "VEX_Call": 192763.177,
    "VEX_Put": 26951343.424,
    "VEX_Total": 27144106.601,
    "VEX_Ratio": 0.007152,
    "CEX_Call": -12252075.161,
    "CEX_Put": 12714514.563,
    "CEX_Total": 462439.402,
    "CEX_Ratio": -0.963629
}