{
    "timestamp": "2025-06-30 09:40:51",
    "cum_gam": null,
    "cum_vec": 7444.049670419157,
    "DEX_Call": 9178.888,
    "DEX_Put": -2809.688,
    "DEX_Total": 6369.2,
    "DEX_Ratio": 3.266871,
    "GEX_Call": 14335392.146,
    "GEX_Put": -7406850.294,
    "GEX_Total": 6928541.852,
    "GEX_Ratio": 1.935424,
    "VEX_Call": 4940606.033,
    "VEX_Put": 21812471.024,
    "VEX_Total": 26753077.057,
    "VEX_Ratio": 0.226504,
    "CEX_Call": 17399809.36,
    "CEX_Put": 25935926.938,
    "CEX_Total": 43335736.298,
    "CEX_Ratio": 0.670877
}