{
    "timestamp": "2025-10-23 07:18:04",
    "cum_gam": null,
    "cum_vec": 8059.269857711995,
    "DEX_Call": 11035.598,
    "DEX_Put": -5475.814,
    "DEX_Total": 5559.784,
    "DEX_Ratio": 2.015335,
    "GEX_Call": 14107228.742,
    "GEX_Put": -12696703.192,
    "GEX_Total": 1410525.55,
    "GEX_Ratio": 1.111094,
    "VEX_Call": -545919.915,
    "VEX_Put": 37474881.355,
    "VEX_Total": 36928961.44,
    "VEX_Ratio": -0.014568,
    "CEX_Call": -10830087.932,
    "CEX_Put": 22511677.516,
    "CEX_Total": 11681589.584,
    "CEX_Ratio": -0.481088
}