{
    "timestamp": "2025-08-29 07:17:52",
    "cum_gam": null,
    "cum_vec": 7529.852313924727,
    "DEX_Call": 7629.082,
    "DEX_Put": -4188.823,
    "DEX_Total": 3440.259,
    "DEX_Ratio": 1.821295,
    "GEX_Call": 14168983.137,
    "GEX_Put": -13784598.029,
    "GEX_Total": 384385.108,
    "GEX_Ratio": 1.027885,
    "VEX_Call": 560465.724,
    "VEX_Put": 29334252.745,
    "VEX_Total": 29894718.469,
    "VEX_Ratio": 0.019106,
    "CEX_Call": -7499541.001,
    "CEX_Put": 24328228.227,
    "CEX_Total": 16828687.226,
    "CEX_Ratio": -0.308265
}