{
    "timestamp": "2025-10-29 11:51:53",
    "cum_gam": null,
    "cum_vec": 8079.605635977464,
    "DEX_Call": 10112.427,
    "DEX_Put": -4259.394,
    "DEX_Total": 5853.033,
    "DEX_Ratio": 2.374147,
    "GEX_Call": 17524389.318,
    "GEX_Put": -12350151.979,
    "GEX_Total": 5174237.339,
    "GEX_Ratio": 1.418961,
    "VEX_Call": 2117611.654,
    "VEX_Put": 37325792.696,
    "VEX_Total": 39443404.35,
    "VEX_Ratio": 0.056733,
    "CEX_Call": -47932546.387,
    "CEX_Put": 53600140.141,
    "CEX_Total": 5667593.754,
    "CEX_Ratio": -0.894262
}