{
    "timestamp": "2025-07-24 07:16:14",
    "cum_gam": 7021.702341101198,
    "cum_vec": 7221.104249239561,
    "DEX_Call": 2366.312,
    "DEX_Put": -717.287,
    "DEX_Total": 1649.025,
    "DEX_Ratio": 3.298975,
    "GEX_Call": 4262387.303,
    "GEX_Put": -2536424.224,
    "GEX_Total": 1725963.079,
    "GEX_Ratio": 1.680471,
    "VEX_Call": -41104.517,
    "VEX_Put": 8055819.071,
    "VEX_Total": 8014714.554,
    "VEX_Ratio": -0.005102,
    "CEX_Call": -708634.796,
    "CEX_Put": 2432135.631,
    "CEX_Total": 1723500.835,
    "CEX_Ratio": -0.291363
}