{
    "timestamp": "2025-10-14 11:49:25",
    "cum_gam": 6452.890921271066,
    "cum_vec": 8193.21645021645,
    "DEX_Call": 237.902,
    "DEX_Put": -341.975,
    "DEX_Total": -104.073,
    "DEX_Ratio": 0.695671,
    "GEX_Call": 1090932.926,
    "GEX_Put": -1290861.415,
    "GEX_Total": -199928.489,
    "GEX_Ratio": 0.84512,
    "VEX_Call": -654527.716,
    "VEX_Put": 1478276.517,
    "VEX_Total": 823748.801,
    "VEX_Ratio": -0.442764,
    "CEX_Call": -734263.761,
    "CEX_Put": 979122.969,
    "CEX_Total": 244859.208,
    "CEX_Ratio": -0.74992
}