{
    "timestamp": "2025-11-25 09:53:56",
    "cum_gam": null,
    "cum_vec": 9357.414951850253,
    "DEX_Call": 2879.048,
    "DEX_Put": -976.761,
    "DEX_Total": 1902.287,
    "DEX_Ratio": 2.947546,
    "GEX_Call": 1408922.343,
    "GEX_Put": -1408104.115,
    "GEX_Total": 818.228,
    "GEX_Ratio": 1.000581,
    "VEX_Call": 699501.06,
    "VEX_Put": 5280662.321,
    "VEX_Total": 5980163.381,
    "VEX_Ratio": 0.132465,
    "CEX_Call": -39272.04,
    "CEX_Put": 578531.817,
    "CEX_Total": 539259.777,
    "CEX_Ratio": -0.067882
}