{
    "timestamp": "2025-09-10 07:04:27",
    "cum_gam": null,
    "cum_vec": 9023.114219958108,
    "DEX_Call": 1805.236,
    "DEX_Put": -846.269,
    "DEX_Total": 958.967,
    "DEX_Ratio": 2.13317,
    "GEX_Call": 2252217.872,
    "GEX_Put": -1998748.031,
    "GEX_Total": 253469.841,
    "GEX_Ratio": 1.126814,
    "VEX_Call": -322061.367,
    "VEX_Put": 9575780.726,
    "VEX_Total": 9253719.359,
    "VEX_Ratio": -0.033633,
    "CEX_Call": -413087.146,
    "CEX_Put": 1536300.166,
    "CEX_Total": 1123213.02,
    "CEX_Ratio": -0.268884
}