{
    "timestamp": "2025-11-18 11:48:08",
    "cum_gam": 3728.0513372366586,
    "cum_vec": 7804.440995192815,
    "DEX_Call": 6532.927,
    "DEX_Put": -4762.73,
    "DEX_Total": 1770.197,
    "DEX_Ratio": 1.371677,
    "GEX_Call": 7022706.702,
    "GEX_Put": -7025091.067,
    "GEX_Total": -2384.365,
    "GEX_Ratio": 0.999661,
    "VEX_Call": -3141927.651,
    "VEX_Put": 16557691.808,
    "VEX_Total": 13415764.157,
    "VEX_Ratio": -0.189756,
    "CEX_Call": -1863950.483,
    "CEX_Put": 2653314.362,
    "CEX_Total": 789363.879,
    "CEX_Ratio": -0.702499
}