{
    "timestamp": "2025-08-20 07:42:16",
    "cum_gam": 6285.08229035683,
    "cum_vec": 7970.985915492958,
    "DEX_Call": 378.204,
    "DEX_Put": -536.464,
    "DEX_Total": -158.26,
    "DEX_Ratio": 0.704994,
    "GEX_Call": 1280171.567,
    "GEX_Put": -1969860.155,
    "GEX_Total": -689688.588,
    "GEX_Ratio": 0.649879,
    "VEX_Call": -702829.742,
    "VEX_Put": 1779339.38,
    "VEX_Total": 1076509.638,
    "VEX_Ratio": -0.394995,
    "CEX_Call": -880624.718,
    "CEX_Put": 1273771.639,
    "CEX_Total": 393146.921,
    "CEX_Ratio": -0.691352
}