{
    "timestamp": "2025-11-18 13:46:59",
    "cum_gam": 5253.981168995514,
    "cum_vec": 7800.3512497511665,
    "DEX_Call": 6234.203,
    "DEX_Put": -5022.766,
    "DEX_Total": 1211.437,
    "DEX_Ratio": 1.241189,
    "GEX_Call": 6783754.451,
    "GEX_Put": -6984785.821,
    "GEX_Total": -201031.37,
    "GEX_Ratio": 0.971219,
    "VEX_Call": -3893422.733,
    "VEX_Put": 16104241.86,
    "VEX_Total": 12210819.127,
    "VEX_Ratio": -0.241764,
    "CEX_Call": -1992114.379,
    "CEX_Put": 2579686.836,
    "CEX_Total": 587572.457,
    "CEX_Ratio": -0.772231
}