{
    "timestamp": "2025-08-19 11:40:26",
    "cum_gam": 5804.124233108244,
    "cum_vec": 8400.0,
    "DEX_Call": 468.317,
    "DEX_Put": -367.73,
    "DEX_Total": 100.587,
    "DEX_Ratio": 1.273535,
    "GEX_Call": 1545946.137,
    "GEX_Put": -1599503.45,
    "GEX_Total": -53557.313,
    "GEX_Ratio": 0.966516,
    "VEX_Call": -546629.356,
    "VEX_Put": 1892863.229,
    "VEX_Total": 1346233.873,
    "VEX_Ratio": -0.288784,
    "CEX_Call": -718000.795,
    "CEX_Put": 1254051.861,
    "CEX_Total": 536051.066,
    "CEX_Ratio": -0.572545
}