{
    "timestamp": "2025-09-19 09:44:39",
    "cum_gam": 8186.399108138238,
    "cum_vec": 8600.0,
    "DEX_Call": 378.391,
    "DEX_Put": -149.455,
    "DEX_Total": 228.936,
    "DEX_Ratio": 2.531806,
    "GEX_Call": 2315886.032,
    "GEX_Put": -1384179.934,
    "GEX_Total": 931706.098,
    "GEX_Ratio": 1.673111,
    "VEX_Call": -206250.394,
    "VEX_Put": 1651836.126,
    "VEX_Total": 1445585.732,
    "VEX_Ratio": -0.124861,
    "CEX_Call": -673064.133,
    "CEX_Put": 2057744.046,
    "CEX_Total": 1384679.913,
    "CEX_Ratio": -0.327088
}