{
    "timestamp": "2025-11-04 13:05:19",
    "cum_gam": 6667.242918556003,
    "cum_vec": 6667.242918556003,
    "DEX_Call": 196.096,
    "DEX_Put": -331.128,
    "DEX_Total": -135.032,
    "DEX_Ratio": 0.592206,
    "GEX_Call": 880859.928,
    "GEX_Put": -1195960.451,
    "GEX_Total": -315100.523,
    "GEX_Ratio": 0.736529,
    "VEX_Call": -651813.623,
    "VEX_Put": 1014108.736,
    "VEX_Total": 362295.113,
    "VEX_Ratio": -0.642745,
    "CEX_Call": -658081.077,
    "CEX_Put": 641837.002,
    "CEX_Total": -16244.075,
    "CEX_Ratio": -1.025309
}