{
    "timestamp": "2025-09-22 07:51:34",
    "cum_gam": null,
    "cum_vec": 7056.23092182967,
    "DEX_Call": 990.186,
    "DEX_Put": -328.664,
    "DEX_Total": 661.522,
    "DEX_Ratio": 3.012761,
    "GEX_Call": 2370057.92,
    "GEX_Put": -1606860.459,
    "GEX_Total": 763197.461,
    "GEX_Ratio": 1.474962,
    "VEX_Call": 287106.881,
    "VEX_Put": 2812620.564,
    "VEX_Total": 3099727.445,
    "VEX_Ratio": 0.102078,
    "CEX_Call": -132350.049,
    "CEX_Put": 1912778.561,
    "CEX_Total": 1780428.512,
    "CEX_Ratio": -0.069193
}