{
    "timestamp": "2025-07-07 09:21:13",
    "cum_gam": null,
    "cum_vec": 7287.867760775823,
    "DEX_Call": 968.695,
    "DEX_Put": -411.078,
    "DEX_Total": 557.617,
    "DEX_Ratio": 2.356475,
    "GEX_Call": 2468772.065,
    "GEX_Put": -1659521.246,
    "GEX_Total": 809250.819,
    "GEX_Ratio": 1.487641,
    "VEX_Call": -48902.41,
    "VEX_Put": 3791352.918,
    "VEX_Total": 3742450.508,
    "VEX_Ratio": -0.012898,
    "CEX_Call": -427680.628,
    "CEX_Put": 2326665.575,
    "CEX_Total": 1898984.947,
    "CEX_Ratio": -0.183817
}