{
    "timestamp": "2025-10-20 12:49:05",
    "cum_gam": 8792.62187088274,
    "cum_vec": 8792.62187088274,
    "DEX_Call": 681.521,
    "DEX_Put": -321.209,
    "DEX_Total": 360.312,
    "DEX_Ratio": 2.121737,
    "GEX_Call": 1825063.306,
    "GEX_Put": -1333299.211,
    "GEX_Total": 491764.095,
    "GEX_Ratio": 1.368833,
    "VEX_Call": -311951.132,
    "VEX_Put": 2975195.307,
    "VEX_Total": 2663244.175,
    "VEX_Ratio": -0.104851,
    "CEX_Call": -516415.167,
    "CEX_Put": 1794690.133,
    "CEX_Total": 1278274.966,
    "CEX_Ratio": -0.287746
}