{
    "timestamp": "2025-11-24 12:03:29",
    "cum_gam": 8399.458565197774,
    "cum_vec": 8562.814070351758,
    "DEX_Call": 242.639,
    "DEX_Put": -285.774,
    "DEX_Total": -43.135,
    "DEX_Ratio": 0.849059,
    "GEX_Call": 980595.717,
    "GEX_Put": -951205.125,
    "GEX_Total": 29390.592,
    "GEX_Ratio": 1.030898,
    "VEX_Call": -628200.804,
    "VEX_Put": 1712332.679,
    "VEX_Total": 1084131.875,
    "VEX_Ratio": -0.366868,
    "CEX_Call": -612097.176,
    "CEX_Put": 1045434.165,
    "CEX_Total": 433336.989,
    "CEX_Ratio": -0.585496
}