{
    "timestamp": "2025-09-24 12:18:28",
    "cum_gam": null,
    "cum_vec": 7004.031130312938,
    "DEX_Call": 932.595,
    "DEX_Put": -566.827,
    "DEX_Total": 365.768,
    "DEX_Ratio": 1.64529,
    "GEX_Call": 2971493.328,
    "GEX_Put": -2861406.013,
    "GEX_Total": 110087.315,
    "GEX_Ratio": 1.038473,
    "VEX_Call": -93957.437,
    "VEX_Put": 2722396.972,
    "VEX_Total": 2628439.535,
    "VEX_Ratio": -0.034513,
    "CEX_Call": -512399.907,
    "CEX_Put": 2424092.563,
    "CEX_Total": 1911692.656,
    "CEX_Ratio": -0.211378
}