{
    "timestamp": "2025-07-25 11:54:46",
    "cum_gam": 7008.780004547374,
    "cum_vec": 7302.361849485441,
    "DEX_Call": 2023.5,
    "DEX_Put": -671.671,
    "DEX_Total": 1351.829,
    "DEX_Ratio": 3.012636,
    "GEX_Call": 4585341.603,
    "GEX_Put": -2550085.938,
    "GEX_Total": 2035255.665,
    "GEX_Ratio": 1.798113,
    "VEX_Call": -7776.061,
    "VEX_Put": 8053659.975,
    "VEX_Total": 8045883.914,
    "VEX_Ratio": -0.000966,
    "CEX_Call": -708023.798,
    "CEX_Put": 2654596.021,
    "CEX_Total": 1946572.223,
    "CEX_Ratio": -0.266716
}