{
    "timestamp": "2025-11-21 09:52:42",
    "cum_gam": 6613.652742252423,
    "cum_vec": 7615.306290481941,
    "DEX_Call": 291.038,
    "DEX_Put": -963.411,
    "DEX_Total": -672.373,
    "DEX_Ratio": 0.302091,
    "GEX_Call": 1132825.223,
    "GEX_Put": -2344452.041,
    "GEX_Total": -1211626.818,
    "GEX_Ratio": 0.483194,
    "VEX_Call": -1326210.187,
    "VEX_Put": 1305414.552,
    "VEX_Total": -20795.635,
    "VEX_Ratio": -1.01593,
    "CEX_Call": -1929968.563,
    "CEX_Put": 1247165.087,
    "CEX_Total": -682803.476,
    "CEX_Ratio": -1.547484
}