{
    "timestamp": "2025-10-15 11:12:57",
    "cum_gam": 5251.388708785881,
    "cum_vec": 7520.29999559733,
    "DEX_Call": 1931.495,
    "DEX_Put": -1229.807,
    "DEX_Total": 701.688,
    "DEX_Ratio": 1.570568,
    "GEX_Call": 2146930.067,
    "GEX_Put": -2204808.975,
    "GEX_Total": -57878.908,
    "GEX_Ratio": 0.973749,
    "VEX_Call": -952825.019,
    "VEX_Put": 9203919.325,
    "VEX_Total": 8251094.306,
    "VEX_Ratio": -0.103524,
    "CEX_Call": -568945.163,
    "CEX_Put": 1531482.542,
    "CEX_Total": 962537.379,
    "CEX_Ratio": -0.3715
}