{
    "timestamp": "2025-07-31 10:16:56",
    "cum_gam": 7009.644912630401,
    "cum_vec": 7461.554041143876,
    "DEX_Call": 2930.012,
    "DEX_Put": -1046.005,
    "DEX_Total": 1884.007,
    "DEX_Ratio": 2.801145,
    "GEX_Call": 6783526.687,
    "GEX_Put": -4766787.952,
    "GEX_Total": 2016738.735,
    "GEX_Ratio": 1.423081,
    "VEX_Call": -535552.098,
    "VEX_Put": 9024210.721,
    "VEX_Total": 8488658.623,
    "VEX_Ratio": -0.059346,
    "CEX_Call": -2728072.579,
    "CEX_Put": 7720119.103,
    "CEX_Total": 4992046.524,
    "CEX_Ratio": -0.353372
}