{
    "timestamp": "2025-09-05 07:20:20",
    "cum_gam": null,
    "cum_vec": null,
    "DEX_Call": 346.735,
    "DEX_Put": -185.037,
    "DEX_Total": 161.698,
    "DEX_Ratio": 1.873868,
    "GEX_Call": 2456216.292,
    "GEX_Put": -1477824.582,
    "GEX_Total": 978391.71,
    "GEX_Ratio": 1.662049,
    "VEX_Call": -529722.438,
    "VEX_Put": 1619939.181,
    "VEX_Total": 1090216.743,
    "VEX_Ratio": -0.327001,
    "CEX_Call": -1114761.811,
    "CEX_Put": 1967542.89,
    "CEX_Total": 852781.079,
    "CEX_Ratio": -0.566576
}