{
    "timestamp": "2025-09-19 08:06:00",
    "cum_gam": 8163.5854341736695,
    "cum_vec": 8600.0,
    "DEX_Call": 358.823,
    "DEX_Put": -177.853,
    "DEX_Total": 180.97,
    "DEX_Ratio": 2.017526,
    "GEX_Call": 2187074.361,
    "GEX_Put": -1528216.436,
    "GEX_Total": 658857.925,
    "GEX_Ratio": 1.431129,
    "VEX_Call": -238330.392,
    "VEX_Put": 1675324.545,
    "VEX_Total": 1436994.153,
    "VEX_Ratio": -0.142259,
    "CEX_Call": -676992.147,
    "CEX_Put": 2035222.188,
    "CEX_Total": 1358230.041,
    "CEX_Ratio": -0.332638
}