{
    "timestamp": "2025-08-15 07:39:21",
    "cum_gam": 7006.461673944746,
    "cum_vec": 7550.30687931865,
    "DEX_Call": 4460.388,
    "DEX_Put": -1963.554,
    "DEX_Total": 2496.834,
    "DEX_Ratio": 2.271589,
    "GEX_Call": 5654699.355,
    "GEX_Put": -4963145.05,
    "GEX_Total": 691554.305,
    "GEX_Ratio": 1.139338,
    "VEX_Call": 2869031.775,
    "VEX_Put": 17526169.669,
    "VEX_Total": 20395201.444,
    "VEX_Ratio": 0.1637,
    "CEX_Call": -326593.535,
    "CEX_Put": 2810786.907,
    "CEX_Total": 2484193.372,
    "CEX_Ratio": -0.116193
}